{"children":{"1":{"verifyBy":{"kind":"equalMathExpression","args":"1/3"},"points":2,"inputBy":{"kind":"math","args":{"hintType":"fraction"}}},"2":{"verifyBy":{"kind":"equalMathExpression","args":"x(4+17x)"},"points":2,"inputBy":{"kind":"math","args":{"hintType":"expression"}}},"3":{"verifyBy":{"kind":"equal","args":0.36},"points":1,"inputBy":{"kind":"number","args":{}}},"4":{"verifyBy":{"kind":"equalOption","args":"C"},"points":2,"inputBy":{"kind":"options"}},"5":{"verifyBy":{"kind":"equalOption","args":"B"},"points":2,"inputBy":{"kind":"options"}},"6":{"children":{"6.1":{"verifyBy":{"kind":"equalMathExpression","args":"4/5x"},"points":1,"inputBy":{"kind":"math","args":{"hintType":"expression"}}},"6.2":{"verifyBy":{"kind":"equalMathExpression","args":"5x"},"points":1,"inputBy":{"kind":"math","args":{"hintType":"expression"}}},"6.3":{"verifyBy":{"kind":"equal","args":125},"points":2,"inputBy":{"kind":"number","args":{"suffix":"testů"}}}}},"7":{"verifyBy":{"kind":"equalMathEquation","args":"5/4"},"points":2,"inputBy":{"kind":"math","args":{"prefix":"y","hintType":"fraction"}}},"8":{"children":{"8.1":{"verifyBy":{"kind":"equal","args":{"podmět":"detox","přísudek":"může zlepšit"}},"points":1,"inputBy":{"podmět":{"kind":"text"},"přísudek":{"kind":"text"}}},"8.2":{"verifyBy":{"kind":"equal","args":{"podmět":"stovky","přísudek":"sklouznou"}},"points":1,"inputBy":{"podmět":{"kind":"text"},"přísudek":{"kind":"text"}}}}},"9":{"children":{"9.1":{"verifyBy":{"kind":"equalOption","args":false},"points":1,"inputBy":{"kind":"bool"}},"9.2":{"verifyBy":{"kind":"equalOption","args":true},"points":1,"inputBy":{"kind":"bool"}},"9.3":{"verifyBy":{"kind":"equalOption","args":true},"points":1,"inputBy":{"kind":"bool"}},"9.4":{"verifyBy":{"kind":"equalOption","args":false},"points":1,"inputBy":{"kind":"bool"}}},"metadata":{"computeBy":{"kind":"group","args":[{"points":2,"min":4},{"points":1,"min":3}]}}},"10":{"children":{"10.1":{"verifyBy":{"kind":"equalOption","args":"A"},"points":1,"inputBy":{"kind":"options"}},"10.2":{"verifyBy":{"kind":"equalOption","args":"C"},"points":1,"inputBy":{"kind":"options"}},"10.3":{"verifyBy":{"kind":"equalOption","args":"E"},"points":1,"inputBy":{"kind":"options"}}}}},"info":{"code":"CTEDU-2026-01-13","maxPoints":22,"questions":{"closed":4,"opened":6}}}