{"children":{"1":{"verifyBy":{"kind":"equalOption","args":"B"},"points":1,"inputBy":{"kind":"options"}},"2":{"verifyBy":{"kind":"equalOption","args":"A"},"points":1,"inputBy":{"kind":"options"}},"3":{"verifyBy":{"kind":"equalOption","args":"A"},"points":1,"inputBy":{"kind":"options"}},"4":{"verifyBy":{"kind":"equalOption","args":"D"},"points":1,"inputBy":{"kind":"options"}},"5":{"verifyBy":{"kind":"equalOption","args":"C"},"points":1,"inputBy":{"kind":"options"}},"6":{"children":{"6.1":{"verifyBy":{"kind":"equalOption","args":"C"},"points":1,"inputBy":{"kind":"options"}},"6.2":{"verifyBy":{"kind":"equalOption","args":"A"},"points":1,"inputBy":{"kind":"options"}},"6.3":{"verifyBy":{"kind":"equalOption","args":"E"},"points":1,"inputBy":{"kind":"options"}}}},"7":{"children":{"7.1":{"verifyBy":{"kind":"equalOption","args":true},"points":1,"inputBy":{"kind":"bool"}},"7.2":{"verifyBy":{"kind":"equalOption","args":true},"points":1,"inputBy":{"kind":"bool"}},"7.3":{"verifyBy":{"kind":"equalOption","args":true},"points":1,"inputBy":{"kind":"bool"}},"7.4":{"verifyBy":{"kind":"equalOption","args":true},"points":1,"inputBy":{"kind":"bool"}}},"metadata":{"computeBy":{"kind":"group","args":[{"points":2,"min":4},{"points":1,"min":3}]}}},"8":{"verifyBy":{"kind":"equalOption","args":"A"},"points":1,"inputBy":{"kind":"options"}},"9":{"verifyBy":{"kind":"equalOption","args":"C"},"points":1,"inputBy":{"kind":"options"}},"10":{"verifyBy":{"kind":"equalOption","args":"B"},"points":1,"inputBy":{"kind":"options"}},"11":{"children":{"11.1":{"verifyBy":{"kind":"equal","args":"lhář"},"points":1,"inputBy":{"kind":"text"}},"11.2":{"verifyBy":{"kind":"equal","args":"smetí"},"points":1,"inputBy":{"kind":"text"}}}},"12":{"children":{"12.1":{"verifyBy":{"kind":"equalOption","args":false},"points":1,"inputBy":{"kind":"bool"}},"12.2":{"verifyBy":{"kind":"equalOption","args":true},"points":1,"inputBy":{"kind":"bool"}},"12.3":{"verifyBy":{"kind":"equalOption","args":false},"points":1,"inputBy":{"kind":"bool"}},"12.4":{"verifyBy":{"kind":"equalOption","args":true},"points":1,"inputBy":{"kind":"bool"}}},"metadata":{"computeBy":{"kind":"group","args":[{"points":2,"min":4},{"points":1,"min":3}]}}},"13":{"children":{"13.1":{"verifyBy":{"kind":"equal","args":{"podmet":"autobus","prisudek":"by nenabral"}},"points":1,"inputBy":{"podmet":{"kind":"text"},"prisudek":{"kind":"text"}}},"13.2":{"verifyBy":{"kind":"matchObjectValues","source":{"podmet":"ochota (a) schopnost","prisudek":"patří"},"args":{"podmet":{"source":"^ochota\\s+(?:a\\s+)?schopnost$","flags":""},"prisudek":{"source":"^patří$","flags":""}}},"points":1,"inputBy":{"podmet":{"kind":"text"},"prisudek":{"kind":"text"}}}}},"14":{"verifyBy":{"kind":"equalSortedOptions","args":["E","B","F","A","D","C"]},"points":3,"inputBy":{"kind":"sortedOptions"}},"15":{"children":{"15.1":{"verifyBy":{"kind":"selfEvaluate","args":{"options":[{"value":0,"name":"0 bodů"},{"value":1,"name":"1 bod"}],"hint":{"kind":"text","content":"např. Přestože naléhal, nabídku odmítla."}}},"inputBy":{"kind":"options","args":[{"value":0,"name":"0 bodů"},{"value":1,"name":"1 bod"}]}},"15.2":{"verifyBy":{"kind":"selfEvaluate","args":{"options":[{"value":0,"name":"0 bodů"},{"value":1,"name":"1 bod"}],"hint":{"kind":"text","content":"např. Sběr hub."}}},"inputBy":{"kind":"options","args":[{"value":0,"name":"0 bodů"},{"value":1,"name":"1 bod"}]}}}},"16":{"verifyBy":{"kind":"equalStringCollection","args":["4","7","11"]},"points":3,"inputBy":[{"kind":"text"},{"kind":"text"},{"kind":"text"}]},"17":{"verifyBy":{"kind":"equalStringCollection","args":["nevídaný","medaili","směle","zpochybňovat"]},"points":4,"inputBy":[{"kind":"text"},{"kind":"text"},{"kind":"text"},{"kind":"text"}]},"18":{"children":{"18.1":{"verifyBy":{"kind":"equalOption","args":false},"points":1,"inputBy":{"kind":"bool"}},"18.2":{"verifyBy":{"kind":"equalOption","args":false},"points":1,"inputBy":{"kind":"bool"}},"18.3":{"verifyBy":{"kind":"equalOption","args":false},"points":1,"inputBy":{"kind":"bool"}},"18.4":{"verifyBy":{"kind":"equalOption","args":true},"points":1,"inputBy":{"kind":"bool"}}},"metadata":{"computeBy":{"kind":"group","args":[{"points":2,"min":4},{"points":1,"min":3}]}}},"19":{"verifyBy":{"kind":"equalOption","args":"A"},"points":1,"inputBy":{"kind":"options"}},"20":{"verifyBy":{"kind":"equalOption","args":"D"},"points":1,"inputBy":{"kind":"options"}},"21":{"children":{"21.1":{"verifyBy":{"kind":"equalOption","args":true},"points":1,"inputBy":{"kind":"bool"}},"21.2":{"verifyBy":{"kind":"equalOption","args":false},"points":1,"inputBy":{"kind":"bool"}},"21.3":{"verifyBy":{"kind":"equalOption","args":false},"points":1,"inputBy":{"kind":"bool"}},"21.4":{"verifyBy":{"kind":"equalOption","args":true},"points":1,"inputBy":{"kind":"bool"}}},"metadata":{"computeBy":{"kind":"group","args":[{"points":2,"min":4},{"points":1,"min":3}]}}},"22":{"verifyBy":{"kind":"equalStringCollection","args":["uprostřed","vedle","mezi"]},"points":3,"inputBy":[{"kind":"text"},{"kind":"text"},{"kind":"text"}]},"23":{"verifyBy":{"kind":"equalOption","args":"C"},"points":1,"inputBy":{"kind":"options"}},"24":{"verifyBy":{"kind":"equalOption","args":"B"},"points":1,"inputBy":{"kind":"options"}},"25":{"children":{"25.1":{"verifyBy":{"kind":"equalOption","args":false},"points":1,"inputBy":{"kind":"bool"}},"25.2":{"verifyBy":{"kind":"equalOption","args":true},"points":1,"inputBy":{"kind":"bool"}},"25.3":{"verifyBy":{"kind":"equalOption","args":true},"points":1,"inputBy":{"kind":"bool"}},"25.4":{"verifyBy":{"kind":"equalOption","args":false},"points":1,"inputBy":{"kind":"bool"}}},"metadata":{"computeBy":{"kind":"group","args":[{"points":2,"min":4},{"points":1,"min":3}]}}},"26":{"verifyBy":{"kind":"equalOption","args":"D"},"points":1,"inputBy":{"kind":"options"}},"27":{"verifyBy":{"kind":"equalOption","args":"D"},"points":1,"inputBy":{"kind":"options"}},"28":{"children":{"28.1":{"verifyBy":{"kind":"equalOption","args":"C"},"points":1,"inputBy":{"kind":"options"}},"28.2":{"verifyBy":{"kind":"equalOption","args":"A"},"points":1,"inputBy":{"kind":"options"}},"28.3":{"verifyBy":{"kind":"equalOption","args":"F"},"points":1,"inputBy":{"kind":"options"}},"28.4":{"verifyBy":{"kind":"equalOption","args":"B"},"points":1,"inputBy":{"kind":"options"}}}}},"info":{"code":"C7PAD24C0T01","maxPoints":50,"questions":{"closed":22,"opened":6}}}