{"children":{"1":{"verifyBy":{"kind":"equalOption","args":"A"},"points":2,"inputBy":{"kind":"options"}},"2":{"verifyBy":{"kind":"equalOption","args":"B"},"points":2,"inputBy":{"kind":"options"}},"3":{"verifyBy":{"kind":"equalMathExpression","args":"-11/10"},"points":1,"inputBy":{"kind":"math","args":{"hintType":"fraction"}}},"4":{"verifyBy":{"kind":"equal","args":{"a":9,"b":81}},"points":1,"inputBy":{"a":{"kind":"number"},"b":{"kind":"number"}}},"5":{"children":{"5.1":{"verifyBy":{"kind":"equal","args":30},"points":1,"inputBy":{"kind":"number","args":{"suffix":"stupňů"}}},"5.2":{"verifyBy":{"kind":"equal","args":50},"points":1,"inputBy":{"kind":"number","args":{"suffix":"stupňů"}}},"5.3":{"verifyBy":{"kind":"equal","args":140},"points":1,"inputBy":{"kind":"number","args":{"suffix":"stupňů"}}}}},"6":{"children":{"6.1":{"verifyBy":{"kind":"equalOption","args":true},"points":1,"inputBy":{"kind":"bool"}},"6.2":{"verifyBy":{"kind":"equalOption","args":true},"points":1,"inputBy":{"kind":"bool"}},"6.3":{"verifyBy":{"kind":"equalOption","args":false},"points":1,"inputBy":{"kind":"bool"}}},"metadata":{"computeBy":{"kind":"group","args":[{"points":4,"min":3},{"points":2,"min":2}]}}},"7":{"children":{"7.1":{"verifyBy":{"kind":"equalOption","args":true},"points":1,"inputBy":{"kind":"bool"}},"7.2":{"verifyBy":{"kind":"equalOption","args":false},"points":1,"inputBy":{"kind":"bool"}},"7.3":{"verifyBy":{"kind":"equalOption","args":false},"points":1,"inputBy":{"kind":"bool"}}},"metadata":{"computeBy":{"kind":"group","args":[{"points":4,"min":3},{"points":2,"min":2}]}}},"8":{"verifyBy":{"kind":"equalOption","args":"B"},"points":2,"inputBy":{"kind":"options"}},"9":{"children":{"9.1":{"verifyBy":{"kind":"equal","args":"obou"},"points":1,"inputBy":{"kind":"text"}},"9.2":{"verifyBy":{"kind":"equal","args":"nabízenou"},"points":1,"inputBy":{"kind":"text"}}}},"10":{"verifyBy":{"kind":"equalOption","args":"C"},"points":1,"inputBy":{"kind":"options"}},"11":{"verifyBy":{"kind":"equalOption","args":"B"},"points":1,"inputBy":{"kind":"options"}},"12":{"verifyBy":{"kind":"equalOption","args":"A"},"points":1,"inputBy":{"kind":"options"}}},"info":{"code":"CTEDU-2026-02-24","maxPoints":19,"questions":{"closed":8,"opened":4}}}